tnfr/__init__.py
tnfr/__init__.pyi
tnfr/_compat.py
tnfr/_generated_version.py
tnfr/_version.pyi
tnfr/alias.py
tnfr/alias.pyi
tnfr/cache.py
tnfr/cache.pyi
tnfr/execution.py
tnfr/execution.pyi
tnfr/flatten.py
tnfr/flatten.pyi
tnfr/gamma.py
tnfr/gamma.pyi
tnfr/glyph_history.py
tnfr/glyph_history.pyi
tnfr/glyph_runtime.py
tnfr/glyph_runtime.pyi
tnfr/immutable.py
tnfr/immutable.pyi
tnfr/initialization.py
tnfr/initialization.pyi
tnfr/io.py
tnfr/io.pyi
tnfr/locking.py
tnfr/locking.pyi
tnfr/node.py
tnfr/node.pyi
tnfr/observers.py
tnfr/observers.pyi
tnfr/ontosim.py
tnfr/ontosim.pyi
tnfr/py.typed
tnfr/rng.py
tnfr/rng.pyi
tnfr/secure_config.py
tnfr/selector.py
tnfr/selector.pyi
tnfr/sense.py
tnfr/sense.pyi
tnfr/structural.py
tnfr/structural.pyi
tnfr/tokens.py
tnfr/tokens.pyi
tnfr/trace.py
tnfr/trace.pyi
tnfr/types.py
tnfr/types.pyi
tnfr/units.py
tnfr/units.pyi
tnfr/backends/__init__.py
tnfr/backends/jax_backend.py
tnfr/backends/numpy_backend.py
tnfr/backends/optimized_numpy.py
tnfr/backends/torch_backend.py
tnfr/cli/__init__.py
tnfr/cli/__init__.pyi
tnfr/cli/arguments.py
tnfr/cli/arguments.pyi
tnfr/cli/execution.py
tnfr/cli/execution.pyi
tnfr/cli/interactive_validator.py
tnfr/cli/utils.py
tnfr/cli/utils.pyi
tnfr/cli/validate.py
tnfr/compat/__init__.py
tnfr/compat/dataclass.py
tnfr/compat/jsonschema_stub.py
tnfr/compat/matplotlib_stub.py
tnfr/compat/numpy_stub.py
tnfr/config/__init__.py
tnfr/config/__init__.pyi
tnfr/config/constants.py
tnfr/config/constants.pyi
tnfr/config/defaults.py
tnfr/config/defaults_core.py
tnfr/config/defaults_init.py
tnfr/config/defaults_metric.py
tnfr/config/feature_flags.py
tnfr/config/feature_flags.pyi
tnfr/config/glyph_constants.py
tnfr/config/init.py
tnfr/config/init.pyi
tnfr/config/operator_names.py
tnfr/config/operator_names.pyi
tnfr/config/physics_derivation.py
tnfr/config/precision_modes.py
tnfr/config/presets.py
tnfr/config/presets.pyi
tnfr/config/security.py
tnfr/config/thresholds.py
tnfr/config/tnfr_config.py
tnfr/constants/__init__.py
tnfr-9.0.4.dist-info/licenses/LICENSE.md
tnfr-9.0.4.dist-info/METADATA
tnfr-9.0.4.dist-info/WHEEL
tnfr-9.0.4.dist-info/entry_points.txt
tnfr-9.0.4.dist-info/top_level.txt
tnfr-9.0.4.dist-info/RECORD
