Metadata-Version: 2.4
Name: tnfr
Version: 9.0.4
Summary: Resonant Fractal Nature Theory (TNFR) - Computational engine for modeling coherent patterns through resonance dynamics
Author: F. F. Martinez Gamo
License-Expression: MIT
Project-URL: Homepage, https://github.com/fermga/TNFR-Python-Engine
Project-URL: Repository, https://github.com/fermga/TNFR-Python-Engine
Project-URL: PyPI, https://pypi.org/project/tnfr/
Project-URL: Citation, https://doi.org/10.5281/zenodo.17602861
Project-URL: Zenodo, https://zenodo.org/records/17602861
Project-URL: Issues, https://github.com/fermga/TNFR-Python-Engine/issues
Project-URL: Documentation, https://fermga.github.io/TNFR-Python-Engine/
Project-URL: GPT, https://chatgpt.com/g/g-67abc78885a88191b2d67f94fd60dc97-tnfr-resonant-fractal-nature-theory
Requires-Python: >=3.10
License-File: LICENSE.md
Provides-Extra: compute-jax
Requires-Dist: jax<1.0,>=0.4; extra == "compute-jax"
Provides-Extra: compute-torch
Requires-Dist: torch<3.0,>=2.1; extra == "compute-torch"
Provides-Extra: serialization
Requires-Dist: pyyaml<7.0,>=6.0; extra == "serialization"
Requires-Dist: orjson<4,>=3; extra == "serialization"
Provides-Extra: viz-basic
Requires-Dist: matplotlib<4.0,>=3.7; extra == "viz-basic"
Provides-Extra: numpy
Provides-Extra: jax
Requires-Dist: jax<1.0,>=0.4; extra == "jax"
Provides-Extra: torch
Requires-Dist: torch<3.0,>=2.1; extra == "torch"
Provides-Extra: yaml
Requires-Dist: pyyaml<7.0,>=6.0; extra == "yaml"
Provides-Extra: orjson
Requires-Dist: orjson<4,>=3; extra == "orjson"
Provides-Extra: viz
Requires-Dist: matplotlib<4.0,>=3.7; extra == "viz"
Provides-Extra: docs
Requires-Dist: sphinx>=7.2; extra == "docs"
Requires-Dist: sphinx-autodoc-typehints>=1.25; extra == "docs"
Requires-Dist: myst-parser>=2.0; extra == "docs"
Requires-Dist: nbsphinx>=0.9; extra == "docs"
Requires-Dist: sphinx-rtd-theme>=1.3; extra == "docs"
Requires-Dist: sphinxcontrib-mermaid>=0.9; extra == "docs"
Requires-Dist: ipykernel>=6; extra == "docs"
Requires-Dist: nbconvert>=7.16; extra == "docs"
Requires-Dist: pypandoc-binary>=1.14; extra == "docs"
Requires-Dist: mkdocs>=1.5; extra == "docs"
Requires-Dist: mkdocs-material>=9.4; extra == "docs"
Requires-Dist: mkdocs-jupyter>=0.24; extra == "docs"
Provides-Extra: test-unit
Requires-Dist: pytest<10,>=7; extra == "test-unit"
Requires-Dist: pytest-cov<8,>=4; extra == "test-unit"
Requires-Dist: pytest-timeout<3,>=2; extra == "test-unit"
Provides-Extra: test-property
Requires-Dist: hypothesis<7,>=6; extra == "test-property"
Requires-Dist: hypothesis-networkx<1.0,>=0.3; extra == "test-property"
Provides-Extra: test-performance
Requires-Dist: pytest-benchmark<6,>=4; extra == "test-performance"
Provides-Extra: test-parallel
Requires-Dist: pytest-xdist<4,>=3; extra == "test-parallel"
Provides-Extra: test-quality
Requires-Dist: pydocstyle<7,>=6; extra == "test-quality"
Requires-Dist: flake8<8,>=5; extra == "test-quality"
Requires-Dist: flake8-pyproject<2.0,>=1.2; extra == "test-quality"
Requires-Dist: vulture<3,>=2; extra == "test-quality"
Provides-Extra: test-all
Requires-Dist: pytest<10,>=7; extra == "test-all"
Requires-Dist: pytest-cov<8,>=4; extra == "test-all"
Requires-Dist: pytest-timeout<3,>=2; extra == "test-all"
Requires-Dist: hypothesis<7,>=6; extra == "test-all"
Requires-Dist: hypothesis-networkx<1.0,>=0.3; extra == "test-all"
Requires-Dist: pytest-benchmark<6,>=4; extra == "test-all"
Requires-Dist: pytest-xdist<4,>=3; extra == "test-all"
Requires-Dist: pydocstyle<7,>=6; extra == "test-all"
Requires-Dist: flake8<8,>=5; extra == "test-all"
Requires-Dist: flake8-pyproject<2.0,>=1.2; extra == "test-all"
Requires-Dist: vulture<3,>=2; extra == "test-all"
Requires-Dist: matplotlib<4.0,>=3.7; extra == "test-all"
Provides-Extra: test
Requires-Dist: pytest<10,>=7; extra == "test"
Requires-Dist: pytest-cov<8,>=4; extra == "test"
Requires-Dist: pytest-timeout<3,>=2; extra == "test"
Requires-Dist: hypothesis<7,>=6; extra == "test"
Requires-Dist: hypothesis-networkx<1.0,>=0.3; extra == "test"
Requires-Dist: pytest-benchmark<6,>=4; extra == "test"
Requires-Dist: pytest-xdist<4,>=3; extra == "test"
Requires-Dist: pydocstyle<7,>=6; extra == "test"
Requires-Dist: flake8<8,>=5; extra == "test"
Requires-Dist: flake8-pyproject<2.0,>=1.2; extra == "test"
Requires-Dist: vulture<3,>=2; extra == "test"
Requires-Dist: matplotlib<4.0,>=3.7; extra == "test"
Provides-Extra: typecheck
Requires-Dist: mypy<2.0,>=1.8; extra == "typecheck"
Requires-Dist: pyright<1.2.0,>=1.1.350; extra == "typecheck"
Requires-Dist: networkx-stubs>=0.0.1; extra == "typecheck"
Requires-Dist: types-cachetools>=6.0.0.0; extra == "typecheck"
Provides-Extra: dev-minimal
Requires-Dist: mypy<2.0,>=1.8; extra == "dev-minimal"
Requires-Dist: black<26,>=23; extra == "dev-minimal"
Requires-Dist: pytest<10,>=7; extra == "dev-minimal"
Requires-Dist: pytest-cov<8,>=4; extra == "dev-minimal"
Requires-Dist: pytest-timeout<3,>=2; extra == "dev-minimal"
Provides-Extra: dev-full
Requires-Dist: pytest<10,>=7; extra == "dev-full"
Requires-Dist: pytest-cov<8,>=4; extra == "dev-full"
Requires-Dist: pytest-timeout<3,>=2; extra == "dev-full"
Requires-Dist: hypothesis<7,>=6; extra == "dev-full"
Requires-Dist: hypothesis-networkx<1.0,>=0.3; extra == "dev-full"
Requires-Dist: pytest-benchmark<6,>=4; extra == "dev-full"
Requires-Dist: pytest-xdist<4,>=3; extra == "dev-full"
Requires-Dist: pydocstyle<7,>=6; extra == "dev-full"
Requires-Dist: flake8<8,>=5; extra == "dev-full"
Requires-Dist: flake8-pyproject<2.0,>=1.2; extra == "dev-full"
Requires-Dist: vulture<3,>=2; extra == "dev-full"
Requires-Dist: matplotlib<4.0,>=3.7; extra == "dev-full"
Requires-Dist: jax<1.0,>=0.4; extra == "dev-full"
Requires-Dist: mypy<2.0,>=1.8; extra == "dev-full"
Requires-Dist: pyright<1.2.0,>=1.1.350; extra == "dev-full"
Requires-Dist: networkx-stubs>=0.0.1; extra == "dev-full"
Requires-Dist: types-cachetools>=6.0.0.0; extra == "dev-full"
Provides-Extra: release
Requires-Dist: python-semantic-release<11,>=10.4; extra == "release"
Requires-Dist: setuptools-scm<10,>=8; extra == "release"
Requires-Dist: build<2,>=1; extra == "release"
Requires-Dist: towncrier<26,>=23; extra == "release"
Dynamic: license-file
